kafka_lib/__init__.py
kafka_lib/consumer.py
kafka_lib/producer.py
microservice_kafka_lib-0.1.0.dist-info/licenses/LICENSE
microservice_kafka_lib-0.1.0.dist-info/METADATA
microservice_kafka_lib-0.1.0.dist-info/WHEEL
microservice_kafka_lib-0.1.0.dist-info/top_level.txt
microservice_kafka_lib-0.1.0.dist-info/RECORD
