Metadata-Version: 2.4
Name: microservice-kafka-lib
Version: 0.1.0
Summary: Async Kafka producer/consumer wrapper for aiokafka
Author-email: Rudolf Kovalevskiy <rudolfkovalevsky86@gmail.com>
License: MIT
Project-URL: Homepage, https://github.com/Rudolf866/microservice-kafka-lib
Project-URL: Source, https://github.com/Rudolf866/microservice-kafka-lib
Project-URL: Issues, https://github.com/Rudolf866/microservice-kafka-lib/issues
Classifier: Programming Language :: Python :: 3
Classifier: Programming Language :: Python :: 3.10
Classifier: Programming Language :: Python :: 3.11
Classifier: License :: OSI Approved :: MIT License
Classifier: Operating System :: OS Independent
Requires-Python: >=3.10
License-File: LICENSE
Requires-Dist: aiokafka>=0.10.0
Dynamic: license-file
